oryum_stack/__init__.py
oryum_stack/cli/__init__.py
oryum_stack/cli/cli.py
oryum_stack/cli/commands/__init__.py
oryum_stack/cli/commands/make_model.py
oryum_stack/cli/commands/new.py
oryum_stack/cli/templates/project/cookiecutter.json
oryum_stack/cli/templates/project/{{cookiecutter.project_slug}}/app.py
oryum_stack/config/__init__.py
oryum_stack/config/settings.py
oryum_stack/utils/__init__.py
oryum_stack/utils/console.py
oryum_stack/utils/i18n.py
oryum_stack/utils/parsers.py
oryum_stack/utils/project.py
oryum_stack/utils/validators.py
oryum_stack_cli-0.1.0.dist-info/METADATA
oryum_stack_cli-0.1.0.dist-info/WHEEL
oryum_stack_cli-0.1.0.dist-info/entry_points.txt
oryum_stack_cli-0.1.0.dist-info/top_level.txt
oryum_stack_cli-0.1.0.dist-info/RECORD
