Metadata-Version: 2.4
Name: oryum-stack-cli
Version: 0.1.0
Summary: CLI para gerar projetos Flask com autenticação e painel administrativo
Home-page: https://github.com/KallebyX/Oryum_stack_cli
Author: Kalleby Evangelho
Author-email: Kalleby Evangelho <kallebyevangelho03@gmail.com>
License: MIT
Requires-Python: >=3.7
Requires-Dist: typer[all]
Requires-Dist: cookiecutter
Requires-Dist: Jinja2
Requires-Dist: SQLAlchemy
Requires-Dist: Flask
Requires-Dist: Flask-Login
Dynamic: author
Dynamic: home-page
Dynamic: requires-python
